{
  "timestamp": "2026-01-08T17:30:46.160344+00:00",
  "generated_at": "2026-01-08 17:30:46",
  "market_sentiment": "Bullish",
  "chain_flows": {
    "chains": [
      {
        "chain": "ethereum",
        "tvl_total": 71191588421,
        "tvl_stable": 56953270736.8,
        "tvl_volatile": 14238317684.199997,
        "stable_inflow_24h": 0.0,
        "native_inflow_24h": 0.0,
        "change_24h_pct": 0.0,
        "tags": [],
        "error": null
      },
      {
        "chain": "solana",
        "tvl_total": 8838829664,
        "tvl_stable": 7071063731.200001,
        "tvl_volatile": 1767765932.7999997,
        "stable_inflow_24h": 2496508.8000000003,
        "native_inflow_24h": 624127.1999999998,
        "change_24h_pct": 0.04,
        "tags": [
          {
            "type": "Buying Power",
            "signal": "Bullish",
            "reason": "Stablecoin inflow dominant - potential buying pressure"
          }
        ],
        "error": null
      },
      {
        "chain": "bsc",
        "tvl_total": 6733273702,
        "tvl_stable": 5386618961.6,
        "tvl_volatile": 1346654740.3999996,
        "stable_inflow_24h": 0.0,
        "native_inflow_24h": 0.0,
        "change_24h_pct": 0.0,
        "tags": [],
        "error": null
      },
      {
        "chain": "arbitrum",
        "tvl_total": 3031566967,
        "tvl_stable": 2425253573.6,
        "tvl_volatile": 606313393.3999999,
        "stable_inflow_24h": 0.0,
        "native_inflow_24h": 0.0,
        "change_24h_pct": 0.0,
        "tags": [],
        "error": null
      },
      {
        "chain": "base",
        "tvl_total": 4660210269,
        "tvl_stable": 3728168215.2000003,
        "tvl_volatile": 932042053.7999998,
        "stable_inflow_24h": 0.0,
        "native_inflow_24h": 0.0,
        "change_24h_pct": 0.0,
        "tags": [],
        "error": null
      },
      {
        "chain": "polygon",
        "tvl_total": 1055064356,
        "tvl_stable": 844051484.8000001,
        "tvl_volatile": 211012871.19999996,
        "stable_inflow_24h": 0.0,
        "native_inflow_24h": 0.0,
        "change_24h_pct": 0.0,
        "tags": [],
        "error": null
      },
      {
        "chain": "avalanche",
        "tvl_total": 1297519834,
        "tvl_stable": 1038015867.2,
        "tvl_volatile": 259503966.79999995,
        "stable_inflow_24h": 0.0,
        "native_inflow_24h": 0.0,
        "change_24h_pct": 0.0,
        "tags": [],
        "error": null
      },
      {
        "chain": "optimism",
        "tvl_total": 295167826,
        "tvl_stable": 88550347.8,
        "tvl_volatile": 206617478.2,
        "stable_inflow_24h": 0.0,
        "native_inflow_24h": 0.0,
        "change_24h_pct": 0.0,
        "tags": [],
        "error": null
      },
      {
        "chain": "tron",
        "tvl_total": 4594838862,
        "tvl_stable": 3675871089.6000004,
        "tvl_volatile": 918967772.3999997,
        "stable_inflow_24h": 0.0,
        "native_inflow_24h": 0.0,
        "change_24h_pct": 0.0,
        "tags": [],
        "error": null
      }
    ],
    "summary": {
      "total_stable_inflow_24h": 2496508.8000000003,
      "total_native_inflow_24h": 624127.1999999998,
      "bullish_signals": 1,
      "bearish_signals": 0,
      "market_sentiment": "Bullish"
    }
  },
  "cex_flows": {
    "exchanges": [
      {
        "exchange": "binance-cex",
        "total_tvl": 171580692922.1551,
        "net_flow_24h": -288337237.2819214,
        "stablecoin_flow_24h": 441459389.6887598,
        "btc_eth_flow_24h": -712553122.4549906,
        "other_flow_24h": -16727189.487458609,
        "stablecoin_pct": 27.205926875554344,
        "asset_breakdown": [
          {
            "symbol": "WETH",
            "flow": -564870248.3744392,
            "category": "btc_eth",
            "current_value": 21787220313.80764
          },
          {
            "symbol": "USDC",
            "flow": 545373005.0196896,
            "category": "stablecoin",
            "current_value": 5557907386.21174
          },
          {
            "symbol": "LTC",
            "flow": 541756666.28385,
            "category": "other",
            "current_value": 541756666.28385
          },
          {
            "symbol": "BNB",
            "flow": -306897816.1463089,
            "category": "other",
            "current_value": 32006701287.91203
          },
          {
            "symbol": "BTC",
            "flow": -138608879.5217514,
            "category": "btc_eth",
            "current_value": 53583400472.0834
          },
          {
            "symbol": "USDT",
            "flow": -102797289.53096008,
            "category": "stablecoin",
            "current_value": 37246382219.2289
          },
          {
            "symbol": "DOGE",
            "flow": -77654768.3657999,
            "category": "other",
            "current_value": 2544090577.07474
          },
          {
            "symbol": "SUI",
            "flow": -63453419.65325,
            "category": "other",
            "current_value": 8.18726
          },
          {
            "symbol": "XRP",
            "flow": -45023678.81023979,
            "category": "other",
            "current_value": 5586611100.87043
          },
          {
            "symbol": "PEPE",
            "flow": -38307856.39400995,
            "category": "other",
            "current_value": 565406859.53582
          }
        ],
        "tags": [
          {
            "type": "Accumulation",
            "signal": "Bullish",
            "reason": "Stablecoin inflow $441.5M - potential buying power"
          },
          {
            "type": "Net Outflow",
            "signal": "Neutral",
            "reason": "Net outflow $288.3M"
          }
        ],
        "error": null
      },
      {
        "exchange": "okx",
        "total_tvl": 22858457667.177795,
        "net_flow_24h": -168733551.37589645,
        "stablecoin_flow_24h": 227389188.16287014,
        "btc_eth_flow_24h": -350800269.75073,
        "other_flow_24h": -44305025.73835006,
        "stablecoin_pct": 32.635241415305316,
        "asset_breakdown": [
          {
            "symbol": "USDT",
            "flow": 223326976.92039013,
            "category": "stablecoin",
            "current_value": 7418230024.67014
          },
          {
            "symbol": "WETH",
            "flow": -201016401.63646984,
            "category": "btc_eth",
            "current_value": 3883747359.28738
          },
          {
            "symbol": "BTC",
            "flow": -143896194.53240013,
            "category": "btc_eth",
            "current_value": 9610675438.81051
          },
          {
            "symbol": "DOGE",
            "flow": -17960623.622050047,
            "category": "other",
            "current_value": 432474754.87968
          },
          {
            "symbol": "SOL",
            "flow": -9706249.753610015,
            "category": "other",
            "current_value": 373300137.68946
          },
          {
            "symbol": "ETH",
            "flow": -6219206.031739995,
            "category": "btc_eth",
            "current_value": 40420738.13536
          },
          {
            "symbol": "USDC",
            "flow": 5679152.228219997,
            "category": "stablecoin",
            "current_value": 25771022.42434
          },
          {
            "symbol": "UNI",
            "flow": -4281988.952679992,
            "category": "other",
            "current_value": 79653944.74219
          },
          {
            "symbol": "PEPE",
            "flow": -3651643.0307800025,
            "category": "other",
            "current_value": 95072685.03332
          },
          {
            "symbol": "LTC",
            "flow": -2064819.4542900026,
            "category": "other",
            "current_value": 222247483.00583
          }
        ],
        "tags": [
          {
            "type": "Accumulation",
            "signal": "Bullish",
            "reason": "Stablecoin inflow $227.4M - potential buying power"
          },
          {
            "type": "Net Outflow",
            "signal": "Neutral",
            "reason": "Net outflow $168.7M"
          }
        ],
        "error": null
      },
      {
        "exchange": "bitfinex",
        "total_tvl": 20280643582.9248,
        "net_flow_24h": -209549117.25241852,
        "stablecoin_flow_24h": -25083089.89476002,
        "btc_eth_flow_24h": -123982594.04752004,
        "other_flow_24h": -59811588.93258998,
        "stablecoin_pct": 2.1776251927636254,
        "asset_breakdown": [
          {
            "symbol": "BTC",
            "flow": -102689774.85853004,
            "category": "btc_eth",
            "current_value": 12774380830.57338
          },
          {
            "symbol": "LEO",
            "flow": -59587466.60918999,
            "category": "other",
            "current_value": 5952837552.52445
          },
          {
            "symbol": "USDT",
            "flow": -23875994.14582002,
            "category": "stablecoin",
            "current_value": 421161990.52764
          },
          {
            "symbol": "WETH",
            "flow": -21292819.188989997,
            "category": "btc_eth",
            "current_value": 956839707.17241
          },
          {
            "symbol": "USDC",
            "flow": -1207095.7489399984,
            "category": "stablecoin",
            "current_value": 17258379.749
          },
          {
            "symbol": "SOL",
            "flow": 494069.8963200003,
            "category": "other",
            "current_value": 75730624.00515
          },
          {
            "symbol": "EURT",
            "flow": -281395.7833,
            "category": "other",
            "current_value": 213504.89136
          },
          {
            "symbol": "LINK",
            "flow": -279480.63682999834,
            "category": "other",
            "current_value": 12304074.08878
          },
          {
            "symbol": "WBT",
            "flow": -157315.79959000088,
            "category": "other",
            "current_value": 16312511.92944
          }
        ],
        "tags": [
          {
            "type": "Withdrawal",
            "signal": "Bullish",
            "reason": "Both stablecoins and BTC/ETH withdrawing - accumulation signal"
          },
          {
            "type": "Net Outflow",
            "signal": "Neutral",
            "reason": "Net outflow $209.5M"
          }
        ],
        "error": null
      },
      {
        "exchange": "bybit",
        "total_tvl": 18913050984.595604,
        "net_flow_24h": -237574834.12607956,
        "stablecoin_flow_24h": -45236727.4287701,
        "btc_eth_flow_24h": -73060402.4597695,
        "other_flow_24h": -117780981.01837014,
        "stablecoin_pct": 33.28712543563264,
        "asset_breakdown": [
          {
            "symbol": "MNT",
            "flow": -76657038.81325006,
            "category": "other",
            "current_value": 2709847522.30745
          },
          {
            "symbol": "USDT",
            "flow": -39332413.25990009,
            "category": "stablecoin",
            "current_value": 5353554146.70023
          },
          {
            "symbol": "WETH",
            "flow": -38340193.71782994,
            "category": "btc_eth",
            "current_value": 1369226802.29949
          },
          {
            "symbol": "USDC",
            "flow": -21984455.566929996,
            "category": "stablecoin",
            "current_value": 379983824.07081
          },
          {
            "symbol": "BTC",
            "flow": -20468750.371159554,
            "category": "btc_eth",
            "current_value": 5594110055.60161
          },
          {
            "symbol": "AVALANCHEUSDC",
            "flow": 19424794.336009994,
            "category": "stablecoin",
            "current_value": 90843042.57604
          },
          {
            "symbol": "ETH",
            "flow": -11614003.219579995,
            "category": "btc_eth",
            "current_value": 136688014.37383
          },
          {
            "symbol": "XRP",
            "flow": -11342538.16824007,
            "category": "other",
            "current_value": 554335117.72504
          },
          {
            "symbol": "SOL",
            "flow": -7057984.747020006,
            "category": "other",
            "current_value": 374150535.31789
          },
          {
            "symbol": "DOGE",
            "flow": -6970631.559780002,
            "category": "other",
            "current_value": 185208456.89844
          }
        ],
        "tags": [
          {
            "type": "Withdrawal",
            "signal": "Bullish",
            "reason": "Both stablecoins and BTC/ETH withdrawing - accumulation signal"
          },
          {
            "type": "Net Outflow",
            "signal": "Neutral",
            "reason": "Net outflow $237.6M"
          }
        ],
        "error": null
      },
      {
        "exchange": "robinhood",
        "total_tvl": 16883847728.890862,
        "net_flow_24h": -190442125.77863884,
        "stablecoin_flow_24h": 0,
        "btc_eth_flow_24h": -181476161.22998953,
        "other_flow_24h": -8965971.80612997,
        "stablecoin_pct": 8.518868495472305e-05,
        "asset_breakdown": [
          {
            "symbol": "BTC",
            "flow": -99826735.15703964,
            "category": "btc_eth",
            "current_value": 12698943672.82685
          },
          {
            "symbol": "WETH",
            "flow": -81649426.07294989,
            "category": "btc_eth",
            "current_value": 3634573339.31821
          },
          {
            "symbol": "SHIB",
            "flow": -3488618.9521799684,
            "category": "other",
            "current_value": 341765509.28525
          },
          {
            "symbol": "PEPE",
            "flow": -2679720.206129998,
            "category": "other",
            "current_value": 39668759.21694
          },
          {
            "symbol": "LINK",
            "flow": -1795911.7206500024,
            "category": "other",
            "current_value": 111402694.56846
          },
          {
            "symbol": "AVAX",
            "flow": -1001720.927170001,
            "category": "other",
            "current_value": 57477481.51957
          }
        ],
        "tags": [
          {
            "type": "Net Outflow",
            "signal": "Neutral",
            "reason": "Net outflow $190.4M"
          }
        ],
        "error": null
      },
      {
        "exchange": "gemini",
        "total_tvl": 7516392195.37003,
        "net_flow_24h": -54965913.02353954,
        "stablecoin_flow_24h": 0,
        "btc_eth_flow_24h": -52256587.28676009,
        "other_flow_24h": -2417099.70083999,
        "stablecoin_pct": 0.42595979264415984,
        "asset_breakdown": [
          {
            "symbol": "WETH",
            "flow": -30796708.99641013,
            "category": "btc_eth",
            "current_value": 1633242784.06422
          },
          {
            "symbol": "BTC",
            "flow": -21459878.29034996,
            "category": "btc_eth",
            "current_value": 5704907181.19431
          },
          {
            "symbol": "PEPE",
            "flow": -1228155.652569998,
            "category": "other",
            "current_value": 19424737.66355
          },
          {
            "symbol": "LINK",
            "flow": -771739.6959099919,
            "category": "other",
            "current_value": 70965765.8205
          },
          {
            "symbol": "UNI",
            "flow": -273380.4658399997,
            "category": "other",
            "current_value": 6422495.30026
          },
          {
            "symbol": "WFTM",
            "flow": -143823.88652000017,
            "category": "other",
            "current_value": 2986460.7026
          }
        ],
        "tags": [
          {
            "type": "Net Outflow",
            "signal": "Neutral",
            "reason": "Net outflow $55.0M"
          }
        ],
        "error": null
      },
      {
        "exchange": "bitget",
        "total_tvl": 7283423059.206984,
        "net_flow_24h": 65281807.24607849,
        "stablecoin_flow_24h": -24422802.82911994,
        "btc_eth_flow_24h": 64295071.9864301,
        "other_flow_24h": 26386349.406819835,
        "stablecoin_pct": 14.705208039845278,
        "asset_breakdown": [
          {
            "symbol": "BTC",
            "flow": 32262200.583630085,
            "category": "btc_eth",
            "current_value": 3103030845.94486
          },
          {
            "symbol": "WETH",
            "flow": 29979650.50809002,
            "category": "btc_eth",
            "current_value": 808545556.24652
          },
          {
            "symbol": "MYX",
            "flow": 22039206.477729976,
            "category": "other",
            "current_value": 536959987.57133
          },
          {
            "symbol": "USDT",
            "flow": -19369112.77277994,
            "category": "stablecoin",
            "current_value": 884097507.2826
          },
          {
            "symbol": "BTCB",
            "flow": 15572196.915039998,
            "category": "other",
            "current_value": 32547046.81434
          },
          {
            "symbol": "BGB",
            "flow": -7416317.740860105,
            "category": "other",
            "current_value": 881213839.47354
          },
          {
            "symbol": "USDC",
            "flow": -7372967.6701900065,
            "category": "stablecoin",
            "current_value": 95111138.78847
          },
          {
            "symbol": "XRP",
            "flow": -3698225.6439800262,
            "category": "other",
            "current_value": 251728670.8618
          },
          {
            "symbol": "ETH",
            "flow": 2053220.8947099969,
            "category": "btc_eth",
            "current_value": 34936674.42218
          },
          {
            "symbol": "PEPE",
            "flow": -1611555.3827500008,
            "category": "other",
            "current_value": 20291650.21123
          }
        ],
        "tags": [
          {
            "type": "Net Inflow",
            "signal": "Neutral",
            "reason": "Net inflow $65.3M"
          }
        ],
        "error": null
      },
      {
        "exchange": "gate",
        "total_tvl": 6646022053.169246,
        "net_flow_24h": -109973951.99904537,
        "stablecoin_flow_24h": -18476518.839859877,
        "btc_eth_flow_24h": -24721817.92284002,
        "other_flow_24h": -64054987.68313983,
        "stablecoin_pct": 16.16138019663291,
        "asset_breakdown": [
          {
            "symbol": "GT",
            "flow": -43707637.334499836,
            "category": "other",
            "current_value": 1156955340.5408
          },
          {
            "symbol": "WETH",
            "flow": -23542463.75035,
            "category": "btc_eth",
            "current_value": 1174777493.39622
          },
          {
            "symbol": "USDT",
            "flow": -18566176.80372989,
            "category": "stablecoin",
            "current_value": 723058344.18192
          },
          {
            "symbol": "DOGE",
            "flow": -14067070.233969986,
            "category": "other",
            "current_value": 299182370.91921
          },
          {
            "symbol": "BTCB",
            "flow": 10573901.45379,
            "category": "other",
            "current_value": 12320425.17425
          },
          {
            "symbol": "WEMIX",
            "flow": 5083889.35748,
            "category": "other",
            "current_value": 6120298.63055
          },
          {
            "symbol": "GTBTC",
            "flow": -4167389.9233500063,
            "category": "other",
            "current_value": 267591312.92963
          },
          {
            "symbol": "XRP",
            "flow": -3651600.5030100048,
            "category": "other",
            "current_value": 104360831.68856
          },
          {
            "symbol": "SOL",
            "flow": -2640345.4402099997,
            "category": "other",
            "current_value": 46407937.97657
          },
          {
            "symbol": "PIPPIN",
            "flow": 2231453.0893,
            "category": "other",
            "current_value": 8139776.46792
          }
        ],
        "tags": [
          {
            "type": "Withdrawal",
            "signal": "Bullish",
            "reason": "Both stablecoins and BTC/ETH withdrawing - accumulation signal"
          },
          {
            "type": "Net Outflow",
            "signal": "Neutral",
            "reason": "Net outflow $110.0M"
          }
        ],
        "error": null
      },
      {
        "exchange": "htx",
        "total_tvl": 6138046706.767427,
        "net_flow_24h": -94984941.32651329,
        "stablecoin_flow_24h": -64939941.904929996,
        "btc_eth_flow_24h": -8594451.09002001,
        "other_flow_24h": -21265001.098929994,
        "stablecoin_pct": 22.11187667784858,
        "asset_breakdown": [
          {
            "symbol": "AETHUSDT",
            "flow": -999072585.2292601,
            "category": "stablecoin",
            "current_value": 294596916.34262
          },
          {
            "symbol": "USDT",
            "flow": 937212647.8487401,
            "category": "stablecoin",
            "current_value": 1006999890.48493
          },
          {
            "symbol": "TRON",
            "flow": -17095975.261950016,
            "category": "other",
            "current_value": 2753424834.03534
          },
          {
            "symbol": "STETH",
            "flow": -5854570.942389965,
            "category": "btc_eth",
            "current_value": 309934353.85381
          },
          {
            "symbol": "BTC",
            "flow": -4757062.504950047,
            "category": "btc_eth",
            "current_value": 845983786.98523
          },
          {
            "symbol": "STUSDT",
            "flow": -4369755.769940004,
            "category": "stablecoin",
            "current_value": 34523893.96329
          },
          {
            "symbol": "WETH",
            "flow": 2437450.62369,
            "category": "btc_eth",
            "current_value": 17848899.16197
          },
          {
            "symbol": "USDC",
            "flow": 2273664.5319,
            "category": "stablecoin",
            "current_value": 9175116.058
          },
          {
            "symbol": "DOGE",
            "flow": -1424482.5594099984,
            "category": "other",
            "current_value": 49110458.93133
          },
          {
            "symbol": "HTX",
            "flow": -1037219.461139977,
            "category": "other",
            "current_value": 440762027.92657
          }
        ],
        "tags": [
          {
            "type": "Net Outflow",
            "signal": "Neutral",
            "reason": "Net outflow $95.0M"
          }
        ],
        "error": null
      },
      {
        "exchange": "mexc",
        "total_tvl": 4847544185.963898,
        "net_flow_24h": -16758098.31821251,
        "stablecoin_flow_24h": -3196512.634189977,
        "btc_eth_flow_24h": -9061274.24948001,
        "other_flow_24h": -2139505.159220005,
        "stablecoin_pct": 62.56760232074713,
        "asset_breakdown": [
          {
            "symbol": "BTC",
            "flow": -8085766.385659993,
            "category": "btc_eth",
            "current_value": 521290056.95349
          },
          {
            "symbol": "XRP",
            "flow": -5383380.822909996,
            "category": "other",
            "current_value": 97330159.60095
          },
          {
            "symbol": "MX",
            "flow": 5280094.877099991,
            "category": "other",
            "current_value": 699297148.70427
          },
          {
            "symbol": "BTCB",
            "flow": 2333236.8478200026,
            "category": "other",
            "current_value": 19097460.08144
          },
          {
            "symbol": "USDT",
            "flow": -2267976.0681200027,
            "category": "stablecoin",
            "current_value": 2176433185.45205
          },
          {
            "symbol": "ETH",
            "flow": -1403355.159649998,
            "category": "btc_eth",
            "current_value": 19332066.84921
          },
          {
            "symbol": "USDC",
            "flow": -1195109.7853600085,
            "category": "stablecoin",
            "current_value": 96612230.34446
          },
          {
            "symbol": "PEPE",
            "flow": -1070761.1598300003,
            "category": "other",
            "current_value": 14185574.58339
          },
          {
            "symbol": "USDT0",
            "flow": 806785.3939500004,
            "category": "stablecoin",
            "current_value": 39143141.71203
          },
          {
            "symbol": "RENDER",
            "flow": -507320.89152000006,
            "category": "other",
            "current_value": 7402182.20791
          }
        ],
        "tags": [],
        "error": null
      }
    ],
    "summary": {
      "total_stablecoin_flow_24h": 487492984.3200002,
      "total_btc_eth_flow_24h": -1472211608.5056696,
      "total_net_flow_24h": -1306037963.236187,
      "bullish_signals": 5,
      "bearish_signals": 0,
      "market_sentiment": "Bullish"
    }
  },
  "stablecoin_marketcap": 305879359284.9333,
  "execution_time_seconds": 4.355324
}